saopaulo/__about__.py
saopaulo/__init__.py
saopaulo-0.0.1.dist-info/METADATA
saopaulo-0.0.1.dist-info/WHEEL
saopaulo-0.0.1.dist-info/licenses/LICENSE.txt
saopaulo-0.0.1.dist-info/RECORD
